paress2/__init__.py
paress2/__version__.py
paress2/browser_checker.py
paress2/main.py
paress2-0.1.7.dist-info/LICENSE
paress2-0.1.7.dist-info/METADATA
paress2-0.1.7.dist-info/WHEEL
paress2-0.1.7.dist-info/top_level.txt
paress2-0.1.7.dist-info/RECORD
