Metadata-Version: 2.1
Name: paress2
Version: 0.1.7
Summary: Paress2 is a Python package for downloading images from the Pares2 website.
Home-page: https://github.com/jairomelo/paress2
Author: Jairo Antonio Melo
Author-email: jairoantoniomelo@gmail.com
License: GNU General Public License v3.0
Keywords: python,paress,paress2,pares2.0,archivos históricos,historical files,historical documents,historical images,historical photos,historical pictures
Classifier: Programming Language :: Python :: 3.7
Classifier: Programming Language :: Python :: 3.8
Classifier: Programming Language :: Python :: 3.9
Classifier: Programming Language :: Python :: 3.10
Classifier: License :: OSI Approved :: GNU General Public License v3 (GPLv3)
Classifier: Operating System :: OS Independent
Requires: Python (>=3.7)
License-File: LICENSE
Requires-Dist: selenium (<5.0.0,>=4.8.2)
Requires-Dist: webdriver-manager (<4.0.0,>=3.8.5)
